lfu_cache/__about__.py
lfu_cache/__init__.py
lfu_cache/dllist.py
lfu_cache/exceptions.py
lfu_cache/lfu_cache.py
tests/__init__.py
tests/test_dllist.py
tests/test_lfu.py
python_lfu-0.0.1.dist-info/LICENSE
python_lfu-0.0.1.dist-info/METADATA
python_lfu-0.0.1.dist-info/WHEEL
python_lfu-0.0.1.dist-info/top_level.txt
python_lfu-0.0.1.dist-info/RECORD
